apischema/__init__.py
apischema/aliases.py
apischema/cache.py
apischema/constraints.py
apischema/dataclasses.py
apischema/dependencies.py
apischema/discriminators.py
apischema/fields.py
apischema/methods.py
apischema/ordering.py
apischema/py.typed
apischema/recursion.py
apischema/schemas.py
apischema/settings.py
apischema/std_types.py
apischema/tagged_unions.py
apischema/type_names.py
apischema/types.py
apischema/typing.py
apischema/utils.py
apischema/visitor.py
apischema/conversions/__init__.py
apischema/conversions/conversions.py
apischema/conversions/converters.py
apischema/conversions/utils.py
apischema/conversions/visitor.py
apischema/deserialization/__init__.py
apischema/deserialization/coercion.py
apischema/deserialization/flattened.py
apischema/deserialization/methods.c
apischema/deserialization/methods.py
apischema/graphql/__init__.py
apischema/graphql/interfaces.py
apischema/graphql/resolvers.py
apischema/graphql/schema.py
apischema/graphql/relay/__init__.py
apischema/graphql/relay/connections.py
apischema/graphql/relay/global_identification.py
apischema/graphql/relay/mutations.py
apischema/graphql/relay/utils.py
apischema/json_schema/__init__.py
apischema/json_schema/conversions_resolver.py
apischema/json_schema/patterns.py
apischema/json_schema/refs.py
apischema/json_schema/schema.py
apischema/json_schema/types.py
apischema/json_schema/versions.py
apischema/metadata/__init__.py
apischema/metadata/implem.py
apischema/metadata/keys.py
apischema/objects/__init__.py
apischema/objects/conversions.py
apischema/objects/fields.py
apischema/objects/getters.py
apischema/objects/visitor.py
apischema/serialization/__init__.py
apischema/serialization/errors.py
apischema/serialization/methods.c
apischema/serialization/methods.py
apischema/serialization/serialized_methods.py
apischema/validation/__init__.py
apischema/validation/dependencies.py
apischema/validation/errors.py
apischema/validation/mock.py
apischema/validation/validators.py
apischema-0.19.0.dist-info/LICENSE.txt
apischema-0.19.0.dist-info/METADATA
apischema-0.19.0.dist-info/WHEEL
apischema-0.19.0.dist-info/top_level.txt
apischema-0.19.0.dist-info/RECORD
