Metadata-Version: 2.1
Name: apischema
Version: 0.19.0
Summary: JSON (de)serialization, GraphQL and JSON schema generation using Python typing.
Author-email: Joseph Perez <joperez@hotmail.fr>
License: MIT
Project-URL: Repository, https://github.com/wyfo/apischema
Project-URL: Documentation, https://wyfo.github.io/apischema
Classifier: Development Status :: 4 - Beta
Classifier: Intended Audience :: Developers
Classifier: License :: OSI Approved :: MIT License
Classifier: Programming Language :: Python :: 3.9
Classifier: Programming Language :: Python :: 3.10
Classifier: Programming Language :: Python :: 3.11
Classifier: Programming Language :: Python :: 3.12
Classifier: Programming Language :: Python :: 3.13
Classifier: Topic :: Software Development :: Libraries :: Python Modules
Requires-Python: >=3.9
License-File: LICENSE.txt
Provides-Extra: graphql
Requires-Dist: graphql-core>=3.0.0; extra == "graphql"
Provides-Extra: examples
Requires-Dist: graphql-core>=3.0.0; extra == "examples"
Requires-Dist: attrs; extra == "examples"
Requires-Dist: docstring_parser; extra == "examples"
Requires-Dist: bson; extra == "examples"
Requires-Dist: orjson; extra == "examples"
Requires-Dist: pydantic; extra == "examples"
Requires-Dist: pytest; extra == "examples"
Requires-Dist: sqlalchemy; extra == "examples"
